[
  {
    "itemId": "3d8aa9fc-aab8-4f95-b2a0-ab65a4d25498",
    "quantity": 2,
    "note": "Contrary to popular belief, Lorem Ipsum is not simply random text. It has roots in a piece of classical Latin literature from 45 BC, making it over 2000 years old.",
    "product": {
      "id": "2baa9b65-45a6-4f3f-a5bc-066c2ddd3b67",
      "name": "Flavouring Vanilla Artificial",
      "price": 5.10,
      "image": "http://dummyimage.com/237x100.png/cc0000/ffffff"
    }
  },
  {
    "itemId": "19445789-014e-496a-944e-5abee4a566c1",
    "quantity": 1,
    "note": "Contrary to popular belief, Lorem Ipsum is not simply random text. It has roots in a piece of classical Latin literature from 45 BC, making it over 2000 years old.",
    "product": {
      "id": "5b8da191-d322-4edf-9ab5-129c5946ad59",
      "name": "Chinese Lemon Pork",
      "price": 15.85,
      "image": "http://dummyimage.com/175x100.png/ff4444/ffffff"
    }
  },
  {
    "itemId": "622ac034-61aa-4d01-9722-ee53ead80eb5",
    "quantity": 1,
    "note": "Contrary to popular belief, Lorem Ipsum is not simply random text. It has roots in a piece of classical Latin literature from 45 BC, making it over 2000 years old.",
    "product": {
      "id": "2c782f6c-c26f-4b68-9a00-063a38a1d1f5",
      "name": "Oranges - Navel, 72",
      "price": 9.38,
      "image": "http://dummyimage.com/189x100.png/dddddd/000000"
    }
  },
  {
    "itemId": "3c13c603-4c18-44a0-bd0f-52cbe86ea33c",
    "quantity": 3,
    "note": "Contrary to popular belief, Lorem Ipsum is not simply random text. It has roots in a piece of classical Latin literature from 45 BC, making it over 2000 years old.",
    "product": {
      "id": "beecf9fb-5ed7-418e-bfde-3b6b5ecea08e",
      "name": "Salmon - Fillets",
      "price": 11.08,
      "image": "http://dummyimage.com/113x100.png/5fa2dd/ffffff"
    }
  },
  {
    "itemId": "deef80c6-98e1-4e53-ad28-396befce779d",
    "quantity": 6,
    "note": "Contrary to popular belief, Lorem Ipsum is not simply random text. It has roots in a piece of classical Latin literature from 45 BC, making it over 2000 years old.",
    "product": {
      "id": "3b221093-e285-4792-a59b-f14d019bf27f",
      "name": "Lamb - Ground",
      "price": 10.81,
      "image": "http://dummyimage.com/226x100.png/cc0000/ffffff"
    }
  },
  {
    "itemId": "f3fd671b-e007-46ce-95a6-2eae2bd55008",
    "quantity": 4,
    "note": "Contrary to popular belief, Lorem Ipsum is not simply random text. It has roots in a piece of classical Latin literature from 45 BC, making it over 2000 years old.",
    "product": {
      "id": "8bb24f98-2f2f-4da9-bd70-9216bd9343f2",
      "name": "Liquid Aminios Acid - Braggs",
      "price": 5.81,
      "image": "http://dummyimage.com/157x100.png/ff4444/ffffff"
    }
  },
  {
    "itemId": "4f579e32-06b4-4469-bb3a-910ac738d133",
    "quantity": 6,
    "note": "Contrary to popular belief, Lorem Ipsum is not simply random text. It has roots in a piece of classical Latin literature from 45 BC, making it over 2000 years old.",
    "product": {
      "id": "ca0274f6-2830-43dc-a8b8-83b46eb043d5",
      "name": "Pie Box - Cello Window 2.5",
      "price": 19.97,
      "image": "http://dummyimage.com/241x100.png/dddddd/000000"
    }
  },
  {
    "itemId": "b22f707c-e814-4493-b8ca-ca18e15b8c8e",
    "quantity": 2,
    "note": "Contrary to popular belief, Lorem Ipsum is not simply random text. It has roots in a piece of classical Latin literature from 45 BC, making it over 2000 years old.",
    "product": {
      "id": "b8f5501f-0c26-4ccc-a69b-671e59fbca59",
      "name": "Snapple - Iced Tea Peach",
      "price": 7.40,
      "image": "http://dummyimage.com/213x100.png/cc0000/ffffff"
    }
  },
  {
    "itemId": "843c9e87-df85-4157-a06e-46f7dd85db37",
    "quantity": 1,
    "note": "Contrary to popular belief, Lorem Ipsum is not simply random text. It has roots in a piece of classical Latin literature from 45 BC, making it over 2000 years old.",
    "product": {
      "id": "67b48184-7a1c-475d-907d-2ead96ae2be3",
      "name": "Bay Leaf Ground",
      "price": 18.70,
      "image": "http://dummyimage.com/105x100.png/ff4444/ffffff"
    }
  },
  {
    "itemId": "41619c44-d436-4074-a8e9-8fd31e0c802e",
    "quantity": 5,
    "note": "Contrary to popular belief, Lorem Ipsum is not simply random text. It has roots in a piece of classical Latin literature from 45 BC, making it over 2000 years old.",
    "product": {
      "id": "78b02015-defe-4647-a944-edf99739bb96",
      "name": "Bacardi Mojito",
      "price": 11.01,
      "image": "http://dummyimage.com/189x100.png/5fa2dd/ffffff"
    }
  },
  {
    "itemId": "c828f58a-1de5-42be-acde-1180325467b2",
    "quantity": 4,
    "note": "Contrary to popular belief, Lorem Ipsum is not simply random text. It has roots in a piece of classical Latin literature from 45 BC, making it over 2000 years old.",
    "product": {
      "id": "3b29b342-c011-4eee-809c-53b173c0a0f8",
      "name": "Gherkin",
      "price": 5.20,
      "image": "http://dummyimage.com/209x100.png/cc0000/ffffff"
    }
  },
  {
    "itemId": "63064b0e-f351-45b8-9bee-997e4f9b61d5",
    "quantity": 7,
    "note": "Contrary to popular belief, Lorem Ipsum is not simply random text. It has roots in a piece of classical Latin literature from 45 BC, making it over 2000 years old.",
    "product": {
      "id": "75dc0111-8df7-4e81-8605-694b14bcbc88",
      "name": "Olive - Spread Tapenade",
      "price": 18.71,
      "image": "http://dummyimage.com/209x100.png/dddddd/000000"
    }
  },
  {
    "itemId": "c05bb80b-0f06-4c1e-967b-9fe018008d3b",
    "quantity": 4,
    "note": "Contrary to popular belief, Lorem Ipsum is not simply random text. It has roots in a piece of classical Latin literature from 45 BC, making it over 2000 years old.",
    "product": {
      "id": "02d97e2e-6936-479f-9027-4ea452244c02",
      "name": "Eggs - Extra Large",
      "price": 11.58,
      "image": "http://dummyimage.com/127x100.png/ff4444/ffffff"
    }
  },
  {
    "itemId": "ecac8280-bc62-48d1-9bc0-d4ac33f1d2aa",
    "quantity": 5,
    "note": "Contrary to popular belief, Lorem Ipsum is not simply random text. It has roots in a piece of classical Latin literature from 45 BC, making it over 2000 years old.",
    "product": {
      "id": "bc00f98c-6733-4a2e-81e7-cae345c80600",
      "name": "Cheese - Brie",
      "price": 5.72,
      "image": "http://dummyimage.com/141x100.png/cc0000/ffffff"
    }
  },
  {
    "itemId": "a841175e-9b93-46a8-9354-c42f2100e63c",
    "quantity": 3,
    "note": "Contrary to popular belief, Lorem Ipsum is not simply random text. It has roots in a piece of classical Latin literature from 45 BC, making it over 2000 years old.",
    "product": {
      "id": "834af7b8-82a1-49bb-bba7-fd7aae8a3d32",
      "name": "Lettuce - Red Leaf",
      "price": 7.11,
      "image": "http://dummyimage.com/174x100.png/5fa2dd/ffffff"
    }
  },
  {
    "itemId": "a8cfb8aa-1597-4b6a-8eb2-bc49c530ec2c",
    "quantity": 5,
    "note": "Contrary to popular belief, Lorem Ipsum is not simply random text. It has roots in a piece of classical Latin literature from 45 BC, making it over 2000 years old.",
    "product": {
      "id": "84d2023e-7451-4d12-9d3f-2037f1495b14",
      "name": "Lamb - Shoulder, Boneless",
      "price": 15.55,
      "image": "http://dummyimage.com/152x100.png/dddddd/000000"
    }
  },
  {
    "itemId": "b15d61da-98cf-40d3-898e-043857a96861",
    "quantity": 3,
    "note": "Contrary to popular belief, Lorem Ipsum is not simply random text. It has roots in a piece of classical Latin literature from 45 BC, making it over 2000 years old.",
    "product": {
      "id": "b25fbfec-1118-45c8-af90-00b49e7fcb1c",
      "name": "Oil - Grapeseed Oil",
      "price": 14.48,
      "image": "http://dummyimage.com/134x100.png/cc0000/ffffff"
    }
  },
  {
    "itemId": "3e8a0c0a-5cc7-4a6a-a7fa-2d357ceb7118",
    "quantity": 2,
    "note": "Contrary to popular belief, Lorem Ipsum is not simply random text. It has roots in a piece of classical Latin literature from 45 BC, making it over 2000 years old.",
    "product": {
      "id": "b6e4f765-d79d-4137-9986-884b77ea3357",
      "name": "Syrup - Kahlua Chocolate",
      "price": 10.24,
      "image": "http://dummyimage.com/234x100.png/cc0000/ffffff"
    }
  },
  {
    "itemId": "600c1654-1821-45a0-bd56-bcea6a47c013",
    "quantity": 8,
    "note": "Contrary to popular belief, Lorem Ipsum is not simply random text. It has roots in a piece of classical Latin literature from 45 BC, making it over 2000 years old.",
    "product": {
      "id": "5762bdc5-23ad-4c7a-83a8-3bcda3e776c2",
      "name": "Mix - Cocktail Strawberry Daiquiri",
      "price": 8.73,
      "image": "http://dummyimage.com/199x100.png/5fa2dd/ffffff"
    }
  },
  {
    "itemId": "b7b4c61f-ed67-4f2e-ae1c-5c89dd72256e",
    "quantity": 1,
    "note": "Contrary to popular belief, Lorem Ipsum is not simply random text. It has roots in a piece of classical Latin literature from 45 BC, making it over 2000 years old.",
    "product": {
      "id": "7e07a0b8-2b50-44b9-9b74-9ca5e5b55160",
      "name": "Chicken - Whole Roasting",
      "price": 18.65,
      "image": "http://dummyimage.com/163x100.png/dddddd/000000"
    }
  }
]
